<Widgets>
    <!-- ToolBars in Rebar use these as ImageList -->
    <UiImageList id="imageListFile"

            TransparentColor = "$Transparent"
            />

    <UiImageList id="imageListPosition"

            TransparentColor = "$Transparent"
            />

    <UiImageList id="imageListMeasure"

            TransparentColor = "$Transparent"
            />

    <UiImageList id="imageListTool"

            TransparentColor = "$Transparent"
            />

	<Form id="FormMain"

	            AllowDrop = "true"
	            AutoScaleDimensions = "(6, 12)"
            AutoScaleMode = "Font"
	            BackColor = "$SystemColors.Control"
	            ClientSize = "(955, 689)"
	            DoubleBuffered = "true"
	            KeyPreview = "true"
	            Name = "FormMain"
	            Text = "Cadencii"
	            >
	  <UiPanel id="PanelMain"
		  	Dock = "Fill"
            Size = "(955, 655)"
			>

		<UiToolStripContainer id="toolStripContainer1"
				Dock = "Fill"
	            Location = "(0, 35)"
	            Name = "toolStripContainer1"
	            Size = "(955, 659)"
	            TabIndex = "26"
	            >
	        <_ContentPanel
	            Size = "(955, 612)"
				>
		        <UiVSplitContainer id="splitContainerProperty"
		            FixedPanel = "Panel1"
		            Dock = "Fill"
		            Location = "(0, 14)"
		            Name = "splitContainerProperty"
		            Panel1MinSize = "25"
		            Panel2MinSize = "25"
		            Size = "(112, 348)"
		            SplitterWidth = "4"
		            TabIndex = "20"
		            TabStop = "false"
		            >
		            <_Panel1
			            Anchor = "Top,Bottom,Left,Right"
			            Name = "m_panel1"
			            Size = "(42, 348)"
			            TabIndex = "0"
			            >
			            <PropertyPanelContainer id="mPropertyPanelContainer"
			            	Dock = "Fill" />
		            </_Panel1>
		            <_Panel2
			            Anchor = "Top,Bottom,Left,Right"
			            Location = "(46, 0)"
			            Name = "m_panel2"
			            Size = "(66, 348)"
			            TabIndex = "1"
			            >
						<UiHSplitContainer id="splitContainer1"
							BackColor = "$(212, 212, 212)"
					    	Dock = "Fill"
				            FixedPanel = "Panel2"
				            Location = "(2, 2)"
				            MinimumSize = "(0, 54)"
				            Name = "splitContainer1"
				            Panel1MinSize = "25"
				            Panel2MinSize = "25"
				            Size = "(953, 54)"
				            SplitterWidth = "4"
				            TabIndex = "4"
				            TabStop = "false"
					        >
					        <_Panel1
					            Anchor = "Top,Bottom,Left,Right"
					            Location = "(0, 0)"
					            Name = "m_panel1"
					            Size = "(953, 50)"
					            TabIndex = "0"
						        >
						        <UiHSplitContainer id="splitContainer2"
						        	Dock = "Fill"
						            FixedPanel = "Panel2"
						            Location = "(0, 345)"
						            Name = "splitContainer2"
						            Panel1MinSize = "25"
						            Panel2MinSize = "25"
						            Size = "(115, 134)"
						            SplitterWidth = "4"
						            TabIndex = "23"
						            TabStop = "false"
						            >
						            <_Panel1
							            Anchor = "Top,Bottom,Left,Right"
							            Location = "(0, 0)"
							            Name = "m_panel1"
							            Size = "(115, 25)"
							            TabIndex = "0"
							            >
										<UiPanel id="panel1"
											Dock = "Fill"
								            Location = "(15, 13)"
								            Name = "panel1"
								            Size = "(421, 279)"
								            TabIndex = "24"
								            >
									        <UiPictureBox id="pictKeyLengthSplitter"
									            Anchor = "Bottom,Left"
									            BackColor = "$SystemColors.Control"
									            BorderStyle = "Fixed3D"
						            			Cursor = "$NoMoveHoriz"
									            Location = "(49, 263)"
									            Margin = "(0)"
									            Name = "pictKeyLengthSplitter"
									            Size = "(16, 16)"
									            TabIndex = "20"
									            TabStop = "false"
									            />
										    <PictOverview id="panelOverview"
										            Anchor = "Top,Left,Right"
										            BackColor = "$(106,108,108)"
										            Location = "(0, 1)"
										            Margin = "(0)"
										            Name = "panelOverview"
										            Size = "(700, 45)"
										            TabIndex = "19"
										            TabStop = "false"
										            />
									        <UiPictureBox id="picturePositionIndicator"
									            Anchor = "Top,Left,Right"
									            BackColor = "$DarkGray"
									            Location = "(0, 46)"
									            Margin = "(0)"
									            Name = "picturePositionIndicator"
									            Size = "(700, 48)"
									            TabIndex = "10"
									            TabStop = "false"
									            />
										    <PictPianoRoll id="pictPianoRoll"
									            Anchor = "Top,Bottom,Left,Right"
									            BackColor = "$(240,240,240)"
									            Location = "(0, 94)"
									            Margin = "(0)"
									            Name = "pictPianoRoll"
									            Size = "(405, 169)"
									            TabIndex = "12"
									            TabStop = "false"
									            />
									        <UiVScrollBar id="vScroll"
									            Anchor = "Top,Bottom,Right"
									            Location = "(405, 94)"
									            Name = "vScroll"
									            Size = "(16, 137)"
									            TabIndex = "17"
									            />
									        <UiPictureBox id="pictureBox3"
									            Anchor = "Bottom,Left"
									            BackColor = "$(224,224,224)"
									            Location = "(0, 263)"
									            Margin = "(0)"
									            Name = "pictureBox3"
									            Size = "(49, 16)"
									            TabIndex = "8"
									            TabStop = "false"
									            />
									        <UiPictureBox id="pictureBox2"
									            Anchor = "Bottom,Right"
									            BackColor = "$(224,224,224)"
									            Location = "(405, 231)"
									            Margin = "(0)"
									            Name = "pictureBox2"
									            Size = "(16, 48)"
									            TabIndex = "5"
									            TabStop = "false"
									            />
										    <UiHScrollBar id="hScroll"
									            Anchor = "Bottom,Left,Right"
									            Location = "(65, 263)"
									            Name = "hScroll"
									            Size = "(257, 16)"
									            TabIndex = "16"
									            />
									        <UiHTrackBar id="trackBar"
									            Anchor = "Bottom,Right"
									            AutoSize = "false"
									            Location = "(322, 263)"
									            Margin = "(0)"
									            Maximum = "609"
									            Minimum = "17"
									            Name = "trackBar"
									            Size = "(83, 16)"
									            TabIndex = "15"
									            TabStop = "false"
									            TickFrequency = "100"
									            TickStyle = "None"
									            Value = "17"
									            />
										</UiPanel>
							        </_Panel1>
						            <_Panel2
				        				Anchor = "Bottom,Left,Right"
							            Location = "(0, 29)"
							            Name = "m_panel2"
							            Size = "(115, 105)"
							            TabIndex = "1"
							            >
							            <WaveformZoom id="panelWaveformZoom"
							            	Dock = "Fill"
							            	>
							            	<_WaveView>
							            		<WaveView id="waveView"
													Anchor = "Top,Bottom,Right,Left"
									            	BackColor = "$(212,212,212)"
									            	Location = "(66, 0)"
									            	Margin = "(0)"
									            	Name = "waveView"
									            	Size = "(355, 59)"
									            	TabIndex = "17"
								            		/>
							            	</_WaveView>
							            </WaveformZoom>
							        </_Panel2>
						        </UiHSplitContainer>
					        </_Panel1>
					        <_Panel2
					            Anchor = "Bottom,Left,Right"
					            BorderStyle = "None"
					            Location = "(0, 54)"
					            Name = "m_panel2"
					            Size = "(953, 25)"
					            TabIndex = "1"
						        >
						        <TrackSelector id = "trackSelector"
						        	Dock = "Fill"
						        	 />
						    </_Panel2>
				        </UiHSplitContainer>
		            </_Panel2>
		        </UiVSplitContainer>
	        </_ContentPanel>
			<_BottomToolStripPanel
	            RenderMode = "System"
	            >
			    <UiToolStrip id="toolStripBottom"
			            Dock = "None"
            Location = "(15, 0)"
			            Name = "toolStripBottom"
			            RenderMode = "System"
			            Size = "(347, 25)"
			            TabIndex = "22"
			            >
		            <_Items>

				        <UiToolStripStatusLabel id="toolStripStatusLabel1"

				            Name = "toolStripStatusLabel1"
				            Size = "(101, 20)"
				            Text = "Game Controler"
				            />

				        <UiToolStripStatusLabel id="stripLblGameCtrlMode"

				            Name = "stripLblGameCtrlMode"
				            Size = "(57, 20)"
				            Text = "Disabled"
				            ToolTipText = "Game Controler"
				            />

				        <UiToolStripSeparator id="toolStripSeparator10"

				            Name = "toolStripSeparator10"
				            Size = "(6, 25)"
				            />

				        <UiToolStripStatusLabel id="toolStripStatusLabel2"

				            Name = "toolStripStatusLabel2"
				            Size = "(53, 20)"
				            Text = "MIDI In"
				            />

				        <UiToolStripStatusLabel id="stripLblMidiIn"

				            Name = "stripLblMidiIn"
				            Size = "(57, 20)"
				            Text = "Disabled"
				            ToolTipText = "Midi In Device"
				            />

				        <UiToolStripSeparator id="toolStripSeparator11"

				            Name = "toolStripSeparator11"
				            Size = "(6, 25)"
				            />

				        <UiToolStripButton id="stripBtnStepSequencer"
				            CheckOnClick = "true"
				            ImageTransparentColor = "$Magenta"
				            Name = "stripBtnStepSequencer"
				            Size = "(55, 22)"
				            Text = "Step"
				            />
		            </_Items>
			    </UiToolStrip>
			    <UiStatusStrip id="statusStrip"
			            Dock = "None"
            Location = "(0, 25)"
			            Name = "statusStrip"
			            Size = "(955, 22)"
			            TabIndex = "25"
			            >
			        <_Content>
				        <UiToolStripStatusLabel id="statusLabel"

				            Name = "statusLabel"
				            Size = "(0, 17)"
				            />
			        </_Content>
			    </UiStatusStrip>
		    </_BottomToolStripPanel>
		</UiToolStripContainer>

		<UiHBox id="rebar"
			Size = "(800, 65)"
			Anchor = "Left,Right,Top"
			Dock = "Top">
		  <UiVBox
			Size = "(250, 65)">
		    <UiToolBar id="toolBarFile"
		            Appearance = "Flat"
		            Divider = "false"
		            DropDownArrows = "true"
		            UiImageList = "#imageListFile"
		            Name = "toolBarFile"
		            ShowToolTips = "true"
		            TabIndex = "25"
		            TextAlign = "Right"
		            Wrappable = "false"
		            Width = "150"
		            >
	            <_Buttons>
			        <UiToolBarButton id="stripBtnFileNew"
			            ImageIndex = "0"
			            ToolTipText = "New"
			            />
			        <UiToolBarButton id="stripBtnFileOpen"
			            ImageIndex = "1"
			            ToolTipText = "Open"
			            />
			        <UiToolBarButton id="stripBtnFileSave"
			            ImageIndex = "2"
			            ToolTipText = "Save"
			            />
			        <UiToolBarSeparatorButton id="toolBarButton1" />
			        <UiToolBarButton id="stripBtnCut"
			            ImageIndex = "3"
			            ToolTipText = "Cut"
			            />
			        <UiToolBarButton id="stripBtnCopy"
			            ImageIndex = "4"
			            ToolTipText = "Copy"
			            />
			        <UiToolBarButton id="stripBtnPaste"
			            ImageIndex = "5"
			            ToolTipText = "Paste"
			            />
			        <UiToolBarSeparatorButton id="toolBarButton2" />
			        <UiToolBarButton id="stripBtnUndo"
			            ImageIndex = "6"
			            ToolTipText = "Undo"
			            />
			        <UiToolBarButton id="stripBtnRedo"
			            ImageIndex = "7"
			            ToolTipText = "Redo"
			            />
	            </_Buttons>
			</UiToolBar>
		    <UiToolBar id="toolBarPosition"
		            Appearance = "Flat"
		            Divider = "false"
		            DropDownArrows = "true"
		            UiImageList = "#imageListPosition"
		            Name = "toolBarPosition"
		            ShowToolTips = "true"
		            TabIndex = "25"
		            TextAlign = "Right"
		            Wrappable = "false"
		            Width = "150"
		            >
	            <_Buttons>
			        <UiToolBarButton id="stripBtnMoveTop"
			            ImageIndex = "0"
			            ToolTipText = "MoveTop"
			            />
			        <UiToolBarButton id="stripBtnRewind"
			            ImageIndex = "1"
			            ToolTipText = "Rewind"
			            />
			        <UiToolBarButton id="stripBtnForward"
			            ImageIndex = "2"
			            ToolTipText = "Forward"
			            />
			        <UiToolBarButton id="stripBtnMoveEnd"
			            ImageIndex = "3"
			            ToolTipText = "MoveEnd"
			            />
			        <UiToolBarButton id="stripBtnPlay"
			            ImageIndex = "4"
			            ToolTipText = "Play"
			            />
			        <UiToolBarSeparatorButton id="toolBarButton4" />
			        <UiToolBarButton id="stripBtnScroll"
			            ImageIndex = "6"
			            />
			        <UiToolBarButton id="stripBtnLoop"
			            ImageIndex = "7"
			            />
	            </_Buttons>
			</UiToolBar>
		  </UiVBox>
		  <UiVBox
			Size = "(300, 65)">
		    <UiToolBar id="toolBarMeasure"
		            Appearance = "Flat"
		            Divider = "false"
		            DropDownArrows = "true"
		            UiImageList = "#imageListMeasure"
		            Name = "toolBarMeasure"
		            ShowToolTips = "true"
		            TabIndex = "25"
		            TextAlign = "Right"
		            Wrappable = "false"
		            Width = "220"
		            >
	            <_Buttons>
			        <UiToolBarButton id="stripDDBtnQuantizeParent" />
			        <UiToolBarSeparatorButton id="toolBarButton5" />
			        <UiToolBarToggleButton id="stripBtnStartMarker"
			            ImageIndex = "0"
			            />
			        <UiToolBarToggleButton id="stripBtnEndMarker"
			            ImageIndex = "1"
			            />
	            </_Buttons>
			</UiToolBar>
		    <UiToolBar id="toolBarTool"
		            Appearance = "Flat"
		            Divider = "false"
		            DropDownArrows = "true"
		            UiImageList = "#imageListTool"
		            Name = "toolBarTool"
		            ShowToolTips = "true"
		            TabIndex = "25"
		            TextAlign = "Right"
		            Wrappable = "false"
		            Width = "300"
		            >
	            <_Buttons>
			        <UiToolBarButton id="stripBtnPointer"
			            ImageIndex = "0"
			            Pushed = "true"
			            ToolTipText = "Pointer"
			            />
			        <UiToolBarButton id="stripBtnPencil"
			            ImageIndex = "1"
			            ToolTipText = "Pencil"
			            />
			        <UiToolBarButton id="stripBtnLine"
			            ImageIndex = "2"
			            ToolTipText = "Line"
			            />
			        <UiToolBarButton id="stripBtnEraser"
			            ImageIndex = "3"
			            ToolTipText = "Eraser"
			            />
			        <UiToolBarSeparatorButton id="toolBarButton3" />
			        <UiToolBarButton id="stripBtnGrid"
			            ImageIndex = "4"
			            ToolTipText = "Grid"
			            />
			        <UiToolBarButton id="stripBtnCurve"
			            ImageIndex = "5"
			            ToolTipText = "Curve"
			            />
	            </_Buttons>
		    </UiToolBar>
		  </UiVBox>
		</UiHBox>
      </UiPanel>
      <_MainMenuStrip>
	    <UiMenuStrip id="menuStripMain"
	            Name = "menuStripMain"
	            RenderMode = "System"
	            Text = "menuStrip1"
	            >
            <_Items>

		        <UiToolStripMenuItem id="menuFile"
		            Name = "menuFile"
		            Text = "File(&amp;F)"
		            >
		            <_DropDownItems>
				        <UiToolStripMenuItem id="menuFileNew"
				            Name = "menuFileNew"
				            Text = "New(&amp;N)"
				            />

				        <UiToolStripMenuItem id="menuFileOpen"
				            Name = "menuFileOpen"
				            Text = "Open(&amp;O)"
				            />

				        <UiToolStripMenuItem id="menuFileSave"
				            Name = "menuFileSave"
				            Text = "Save(&amp;S)"
				            />

				        <UiToolStripMenuItem id="menuFileSaveNamed"
				            Name = "menuFileSaveNamed"
				            Text = "Save As(&amp;A)"
				            />

				        <UiToolStripSeparator id="toolStripMenuItem10"
				            Name = "toolStripMenuItem10"
				            />

				        <UiToolStripMenuItem id="menuFileOpenVsq"
				            Name = "menuFileOpenVsq"
				            Text = "Open VSQX/VSQ/Vocaloid Midi(&amp;V)"
				            />

				        <UiToolStripMenuItem id="menuFileOpenUst"
				            Name = "menuFileOpenUst"
				            Text = "Open UTAU Project File(&amp;U)"
				            />

				        <UiToolStripMenuItem id="menuFileImport"
				            Name = "menuFileImport"
				            Text = "Import(&amp;I)"
				            >
				            <_DropDownItems>
						        <UiToolStripMenuItem id="menuFileImportVsq"
						            Name = "menuFileImportVsq"
						            Text = "VSQ File"
						            />
						        <UiToolStripMenuItem id="menuFileImportMidi"
						            Name = "menuFileImportMidi"
						            Text = "Standard MIDI"
						            />
						        <UiToolStripMenuItem id="menuFileImportUst"
						            Name = "menuFileImportUst"
						            Text = "UTAU project file"
						            />
				            </_DropDownItems>
				        </UiToolStripMenuItem>

				        <UiToolStripMenuItem id="menuFileExport"
				            Name = "menuFileExport"
				            Text = "Export(&amp;E)"
				            >
				            <_DropDownItems>
						        <UiToolStripMenuItem id="menuFileExportWave"
						            Name = "menuFileExportWave"
						            Text = "Wave"
						            />
						        <UiToolStripMenuItem id="menuFileExportParaWave"
						            Name = "menuFileExportParaWave"
						            Text = "Serial numbered Wave"
						            />
						        <UiToolStripMenuItem id="menuFileExportVsq"
						            Name = "menuFileExportVsq"
						            Text = "VSQ File"
						            />
						        <UiToolStripMenuItem id="menuFileExportVsqx"
						            Name = "menuFileExportVsqx"
						            Text = "VSQX File"
						            />
						        <UiToolStripMenuItem id="menuFileExportMidi"
						            Name = "menuFileExportMidi"
						            Text = "MIDI"
						            />
						        <UiToolStripMenuItem id="menuFileExportMusicXml"
						            Name = "menuFileExportMusicXml"
						            Text = "MusicXML"
						            />
						        <UiToolStripMenuItem id="menuFileExportUst"
						            Name = "menuFileExportUst"
						            Text = "UTAU Project File (current track)"
						            />
						        <UiToolStripMenuItem id="menuFileExportVxt"
						            Name = "menuFileExportVxt"
						            Text = "Metatext for vConnect"
						            />
				            </_DropDownItems>
						</UiToolStripMenuItem>
				        <UiToolStripSeparator id="toolStripMenuItem11"
				            Name = "toolStripMenuItem11"
				            />
				        <UiToolStripMenuItem id="menuFileRecent"
				            Name = "menuFileRecent"
				            Text = "Recent Files(&amp;R)"
				            >
				            <_DropDownItems>
						        <UiToolStripMenuItem id="menuFileRecentClear"
						            Name = "menuFileRecentClear"
						            Text = "Clear Menu"
						            />
				            </_DropDownItems>
						</UiToolStripMenuItem>

				        <UiToolStripSeparator id="toolStripMenuItem12"
				            Name = "toolStripMenuItem12"
				            />
				        <UiToolStripMenuItem id="menuFileQuit"
				            Name = "menuFileQuit"
				            Text = "Quit(&amp;Q)"
				            />
		            </_DropDownItems>
		        </UiToolStripMenuItem>

		        <UiToolStripMenuItem id="menuEdit"
		            Name = "menuEdit"
		            Text = "Edit(&amp;E)"
		            >
		            <_DropDownItems>

				        <UiToolStripMenuItem id="menuEditUndo"
				            Name = "menuEditUndo"
				            Text = "Undo(&amp;U)"
				            />

				        <UiToolStripMenuItem id="menuEditRedo"
				            Name = "menuEditRedo"
				            Text = "Redo(&amp;R)"
				            />

				        <UiToolStripSeparator id="toolStripMenuItem5"
				            Name = "toolStripMenuItem5"
				            />

				        <UiToolStripMenuItem id="menuEditCut"
				            Name = "menuEditCut"
				            Text = "Cut(&amp;T)"
				            />

				        <UiToolStripMenuItem id="menuEditCopy"
				            Name = "menuEditCopy"
				            Text = "Copy(&amp;C)"
				            />

				        <UiToolStripMenuItem id="menuEditPaste"
				            Name = "menuEditPaste"
				            Text = "Paste(&amp;P)"
				            />

				        <UiToolStripMenuItem id="menuEditDelete"
				            Name = "menuEditDelete"
				            Text = "Delete(&amp;D)"
				            />

				        <UiToolStripSeparator id="toolStripMenuItem19"
				            Name = "toolStripMenuItem19"
				            />

				        <UiToolStripMenuItem id="menuEditAutoNormalizeMode"
				            Name = "menuEditAutoNormalizeMode"
				            Text = "Auto Normalize Mode(&amp;N)"
				            />

				        <UiToolStripSeparator id="toolStripMenuItem20"
				            Name = "toolStripMenuItem20"
				            />

				        <UiToolStripMenuItem id="menuEditSelectAll"
				            Name = "menuEditSelectAll"
				            Text = "Select All(&amp;A)"
				            />

				        <UiToolStripMenuItem id="menuEditSelectAllEvents"
				            Name = "menuEditSelectAllEvents"
				            Text = "Select All Events(&amp;E)"
				            />
		            </_DropDownItems>
				</UiToolStripMenuItem>

		        <UiToolStripMenuItem id="menuVisual"
		            Name = "menuVisual"
		            Text = "View(&amp;V)"
		            >
		            <_DropDownItems>

				        <UiToolStripMenuItem id="menuVisualControlTrack"
				            Checked = "true"
				            CheckOnClick = "true"
				            Name = "menuVisualControlTrack"
				            Text = "Control Track(&amp;C)"
				            />

				        <UiToolStripMenuItem id="menuVisualMixer"
				            Name = "menuVisualMixer"
			            Text = "Mixer(&amp;X)"
				            />

				        <UiToolStripMenuItem id="menuVisualWaveform"

				            CheckOnClick = "true"
				            Name = "menuVisualWaveform"
				            Text = "Waveform(&amp;W)"
				            />

				        <UiToolStripMenuItem id="menuVisualIconPalette"
				            CheckOnClick = "true"
				            Name = "menuVisualIconPalette"
				            Text = "Icon Palette(&amp;I)"
				            />

				        <UiToolStripMenuItem id="menuVisualProperty"
				            CheckOnClick = "true"
				            Name = "menuVisualProperty"
				            Text = "Property Window(&amp;C)"
				            />

				        <UiToolStripMenuItem id="menuVisualOverview"
				            CheckOnClick = "true"
				            Name = "menuVisualOverview"
				            Text = "Overview(&amp;O)"
				            />

				        <UiToolStripMenuItem id="menuVisualPluginUi"
				            Name = "menuVisualPluginUi"
				            Text = "VSTi Plugin UI(&amp;U)"
				            >
				            <_DropDownItems>

						        <UiToolStripMenuItem id="menuVisualPluginUiVocaloid1"
						            Name = "menuVisualPluginUiVocaloid1"
						            Text = "VOCALOID1"
						            />

						        <UiToolStripMenuItem id="menuVisualPluginUiVocaloid2"
						            Name = "menuVisualPluginUiVocaloid2"
						            Text = "VOCALOID2"
						            />

						        <UiToolStripMenuItem id="menuVisualPluginUiAquesTone"
						            Name = "menuVisualPluginUiAquesTone"
						            Text = "AquesTone(&amp;A)"
						            />

						        <UiToolStripMenuItem id="menuVisualPluginUiAquesTone2"
						            Name = "menuVisualPluginUiAquesTone2"
						            Text = "AquesTone2"
						            />
				            </_DropDownItems>
						</UiToolStripMenuItem>

				        <UiToolStripSeparator id="toolStripMenuItem1"
				            Name = "toolStripMenuItem1"
				            />

				        <UiToolStripMenuItem id="menuVisualGridline"
				            CheckOnClick = "true"
				            Name = "menuVisualGridline"
				            Text = "Grid Line(&amp;G)"
				            />

				        <UiToolStripSeparator id="toolStripMenuItem2"
				            Name = "toolStripMenuItem2"
				            />

				        <UiToolStripMenuItem id="menuVisualStartMarker"
				            Name = "menuVisualStartMarker"
				            Text = "Start Marker(&amp;S)"
				            />

				        <UiToolStripMenuItem id="menuVisualEndMarker"
				            Name = "menuVisualEndMarker"
				            Text = "End Marker(&amp;E)"
				            />

				        <UiToolStripSeparator id="toolStripMenuItem3"
				            Name = "toolStripMenuItem3"
				            />

				        <UiToolStripMenuItem id="menuVisualLyrics"
				            Checked = "true"
				            CheckOnClick = "true"
				            Name = "menuVisualLyrics"
				            Text = "Lyric/Phoneme(&amp;L)"
				            />

				        <UiToolStripMenuItem id="menuVisualNoteProperty"
				            Checked = "true"
				            CheckOnClick = "true"
				            Name = "menuVisualNoteProperty"
				            Text = "Note Expression/Vibrato(&amp;N)"
				            />

				        <UiToolStripMenuItem id="menuVisualPitchLine"
				            CheckOnClick = "true"
				            Name = "menuVisualPitchLine"
				            Text = "Pitch Line(&amp;P)"
				            />
		            </_DropDownItems>
		        </UiToolStripMenuItem>

		        <UiToolStripMenuItem id="menuJob"
		            Name = "menuJob"
		            Text = "Job(&amp;J)"
		            >
		            <_DropDownItems>

				        <UiToolStripMenuItem id="menuJobNormalize"
				            Name = "menuJobNormalize"
				            Text = "Normalize Notes(&amp;N)"
				            />

				        <UiToolStripMenuItem id="menuJobInsertBar"
				            Name = "menuJobInsertBar"
				            Text = "Insert Bars(&amp;I)"
				            />

				        <UiToolStripMenuItem id="menuJobDeleteBar"
				            Name = "menuJobDeleteBar"
				            Text = "Delete Bars(&amp;D)"
				            />

				        <UiToolStripMenuItem id="menuJobRandomize"
				            Name = "menuJobRandomize"
				            Text = "Randomize(&amp;R)"
				            />

				        <UiToolStripMenuItem id="menuJobConnect"
				            Name = "menuJobConnect"
				            Text = "Connect Notes(&amp;C)"
				            />

				        <UiToolStripMenuItem id="menuJobLyric"
				            Name = "menuJobLyric"
				            Text = "Insert Lyrics(&amp;L)"
				            />

				        <UiToolStripMenuItem id="menuJobRewire"
				            Enabled = "false"
				            Name = "menuJobRewire"
				            Text = "Import ReWire Host Tempo(&amp;T)"
				            />

				        <UiToolStripMenuItem id="menuJobReloadVsti"
				            Name = "menuJobReloadVsti"
				            Text = "Reload VSTi(&amp;R)"
				            Visible = "false"
				            />
		            </_DropDownItems>
		        </UiToolStripMenuItem>

		        <UiToolStripMenuItem id="menuTrack"
		            Name = "menuTrack"
		            Text = "Track(&amp;T)"
		            >
		            <_DropDownItems>

				        <UiToolStripMenuItem id="menuTrackOn"
				            Name = "menuTrackOn"
				            Text = "Track On(&amp;K)"
				            />

				        <UiToolStripSeparator id="toolStripMenuItem21"
				            Name = "toolStripMenuItem21"
				            />

				        <UiToolStripMenuItem id="menuTrackAdd"
				            Name = "menuTrackAdd"
				            Text = "Add Track(&amp;A)"
				            />

				        <UiToolStripMenuItem id="menuTrackCopy"
				            Name = "menuTrackCopy"
				            Text = "Copy Track(&amp;C)"
				            />

				        <UiToolStripMenuItem id="menuTrackChangeName"
				            Name = "menuTrackChangeName"
				            Text = "Rename Track"
				            />

				        <UiToolStripMenuItem id="menuTrackDelete"
				            Name = "menuTrackDelete"
				            Text = "Delete Track(&amp;D)"
				            />

				        <UiToolStripSeparator id="toolStripMenuItem22"
				            Name = "toolStripMenuItem22"
				            />

				        <UiToolStripMenuItem id="menuTrackRenderCurrent"
				            Name = "menuTrackRenderCurrent"
				            Text = "Render Current Track(&amp;T)"
				            />

				        <UiToolStripMenuItem id="menuTrackRenderAll"
				            Enabled = "false"
				            Name = "menuTrackRenderAll"
				            Text = "Render All Tracks(&amp;S)"
				            />

				        <UiToolStripSeparator id="toolStripMenuItem23"
				            Name = "toolStripMenuItem23"
				            />

				        <UiToolStripMenuItem id="menuTrackOverlay"
				            Name = "menuTrackOverlay"
				            Text = "Overlay(&amp;O)"
				            />

				        <UiToolStripMenuItem id="menuTrackRenderer"
				            Name = "menuTrackRenderer"
				            Text = "Renderer(&amp;R)"
				            >
				            <_DropDownItems>

						        <UiToolStripMenuItem id="menuTrackRendererVOCALOID1"
						            Name = "menuTrackRendererVOCALOID1"
						            Text = "VOCALOID1(&amp;1)"
						            />

						        <UiToolStripMenuItem id="menuTrackRendererVOCALOID2"
						            Name = "menuTrackRendererVOCALOID2"
						            Text = "VOCALOID2(&amp;2)"
						            />

						        <UiToolStripMenuItem id="menuTrackRendererUtau"
						            Name = "menuTrackRendererUtau"
						            Text = "UTAU(&amp;3)"
						            />

						        <UiToolStripMenuItem id="menuTrackRendererVCNT"
						            Name = "menuTrackRendererVCNT"
						            Text = "vConnect-STAND(&amp;4)"
						            />

						        <UiToolStripMenuItem id="menuTrackRendererAquesTone"
						            Name = "menuTrackRendererAquesTone"
						            Text = "AquesTone(&amp;5)"
						            />

						        <UiToolStripMenuItem id="menuTrackRendererAquesTone2"
						            Name = "menuTrackRendererAquesTone2"
						            Text = "AquesTone2(&amp;6)"
						            />
				            </_DropDownItems>
						</UiToolStripMenuItem>

				        <UiToolStripSeparator id="toolStripMenuItem4"
				            Name = "toolStripMenuItem4"
				            />

				        <UiToolStripMenuItem id="menuTrackBgm"
				            Name = "menuTrackBgm"
				            Text = "BGM(&amp;B)"
				            />
		            </_DropDownItems>
				</UiToolStripMenuItem>

		        <UiToolStripMenuItem id="menuLyric"
		            Name = "menuLyric"
		            Text = "Lyrics(&amp;L)"
		            >
		            <_DropDownItems>

				        <UiToolStripMenuItem id="menuLyricExpressionProperty"
				            Name = "menuLyricExpressionProperty"
				            Text = "Note Expression Property(&amp;E)"
				            />

				        <UiToolStripMenuItem id="menuLyricVibratoProperty"
				            Name = "menuLyricVibratoProperty"
				            Text = "Note Vibrato Property(&amp;V)"
				            />

				        <UiToolStripMenuItem id="menuLyricApplyUtauParameters"
				            Name = "menuLyricApplyUtauParameters"
				            Text = "Apply UTAU Parameters(&amp;A)"
				            />

				        <UiToolStripMenuItem id="menuLyricPhonemeTransformation"
				            Name = "menuLyricPhonemeTransformation"
				            Text = "Phoneme Transformation(&amp;T)"
				            />

				        <UiToolStripMenuItem id="menuLyricDictionary"
				            Name = "menuLyricDictionary"
				            Text = "User Word Dictionary(&amp;C)"
				            />

				        <UiToolStripMenuItem id="menuLyricCopyVibratoToPreset"
				            Name = "menuLyricCopyVibratoToPreset"
				            Text = "Copy vibrato config to preset(&amp;P)"
				            />
		            </_DropDownItems>
				</UiToolStripMenuItem>

		        <UiToolStripMenuItem id="menuScript"
		            Name = "menuScript"
		            Text = "Script(&amp;C)"
		            >
		            <_DropDownItems>

				        <UiToolStripMenuItem id="menuScriptUpdate"
				            Name = "menuScriptUpdate"
				            Text = "Update Script List(&amp;U)"
				            />
		            </_DropDownItems>
		        </UiToolStripMenuItem>

		        <UiToolStripMenuItem id="menuSetting"
		            Name = "menuSetting"
		            Text = "Setting(&amp;S)"
		            >
		            <_DropDownItems>

				        <UiToolStripMenuItem id="menuSettingPreference"
				            Name = "menuSettingPreference"
				            Text = "Preference(&amp;P)"
				            />

				        <UiToolStripMenuItem id="menuSettingSequence"
				            Name = "menuSettingSequence"
				            Text = "Sequence config(&amp;S)"
				            />

				        <UiToolStripMenuItem id="menuSettingPositionQuantize"
				            Name = "menuSettingPositionQuantize"
				            Text = "Quantize(&amp;Q)"
				            >
				            <_DropDownItems>

						        <UiToolStripMenuItem id="menuSettingPositionQuantize04"
						            Name = "menuSettingPositionQuantize04"
						            Text = "1/4"
						            />

						        <UiToolStripMenuItem id="menuSettingPositionQuantize08"
						            Name = "menuSettingPositionQuantize08"
						            Text = "1/8"
						            />

						        <UiToolStripMenuItem id="menuSettingPositionQuantize16"
						            Name = "menuSettingPositionQuantize16"
						            Text = "1/16"
						            />

						        <UiToolStripMenuItem id="menuSettingPositionQuantize32"
						            Name = "menuSettingPositionQuantize32"
						            Text = "1/32"
						            />

						        <UiToolStripMenuItem id="menuSettingPositionQuantize64"
						            Name = "menuSettingPositionQuantize64"
						            Text = "1/64"
						            />

						        <UiToolStripMenuItem id="menuSettingPositionQuantize128"
						            Name = "menuSettingPositionQuantize128"
						            Text = "1/128"
						            />

						        <UiToolStripMenuItem id="menuSettingPositionQuantizeOff"
						            Name = "menuSettingPositionQuantizeOff"
						            Text = "Off"
						            />

						        <UiToolStripSeparator id="toolStripMenuItem9"
						            Name = "toolStripMenuItem9"
						            />

						        <UiToolStripMenuItem id="menuSettingPositionQuantizeTriplet"
						            Name = "menuSettingPositionQuantizeTriplet"
						            Text = "Triplet"
						            />
				            </_DropDownItems>
						</UiToolStripMenuItem>

				        <UiToolStripSeparator id="toolStripMenuItem8"
				            Name = "toolStripMenuItem8"
				            />

				        <UiToolStripMenuItem id="menuSettingGameControler"
				            Name = "menuSettingGameControler"
				            Text = "Game Controler(&amp;G)"
				            >
				            <_DropDownItems>

						        <UiToolStripMenuItem id="menuSettingGameControlerSetting"
						            Name = "menuSettingGameControlerSetting"
						            Text = "Setting(&amp;S)"
						            />

						        <UiToolStripMenuItem id="menuSettingGameControlerLoad"
						            Name = "menuSettingGameControlerLoad"
						            Text = "Load(&amp;L)"
						            />

						        <UiToolStripMenuItem id="menuSettingGameControlerRemove"
						            Name = "menuSettingGameControlerRemove"
						            Text = "Remove(&amp;R)"
						            />
				            </_DropDownItems>
			            </UiToolStripMenuItem>

				        <UiToolStripMenuItem id="menuSettingPaletteTool"
				            Name = "menuSettingPaletteTool"
				            Text = "Palette Tool(&amp;T)"
				            />

				        <UiToolStripMenuItem id="menuSettingShortcut"
				            Name = "menuSettingShortcut"
				            Text = "Shortcut Key(&amp;K)"
				            />

				        <UiToolStripMenuItem id="menuSettingVibratoPreset"
				            Name = "menuSettingVibratoPreset"
				            Text = "Vibrato preset(&amp;V)"
				            />

				        <UiToolStripSeparator id="toolStripMenuItem6"
				            Name = "toolStripMenuItem6"
				            />

				        <UiToolStripMenuItem id="menuSettingDefaultSingerStyle"
				            Name = "menuSettingDefaultSingerStyle"
				            Text = "Singing Style Defaults(&amp;D)"
				            />
			        </_DropDownItems>
				</UiToolStripMenuItem>

		        <UiToolStripMenuItem id="menuTools"
		            Name = "menuTools"
		            Text = "Tools(&amp;O)"
		            >
		            <_DropDownItems>

				        <UiToolStripMenuItem id="menuToolsCreateVConnectSTANDDb"
				            Name = "menuToolsCreateVConnectSTANDDb"
				            Text = "Create vConnect-STAND DB"
				            />
		            </_DropDownItems>
				</UiToolStripMenuItem>

		        <UiToolStripMenuItem id="menuHelp"
		            Name = "menuHelp"
		            Text = "Help(&amp;H)"
		            >
		            <_DropDownItems>
				        <UiToolStripMenuItem id="menuHelpAbout"
				            Name = "menuHelpAbout"
				            Text = "About Cadencii(&amp;A)"
				            />

				        <UiToolStripMenuItem id="menuHelpManual"
				            Name = "menuHelpManual"
				            Text = "Manual (PDF)"
				            />

				        <UiToolStripMenuItem id="menuHelpCheckForUpdates"
				            Name = "menuHelpCheckForUpdates"
				            Text = "Check For Updates"
				            />

				        <UiToolStripMenuItem id="menuHelpLog"
				            Name = "menuHelpLog"
				            Text = "Log(&amp;L)"
				            >
				            <_DropDownItems>
						        <UiToolStripMenuItem id="menuHelpLogSwitch"
						            CheckOnClick = "true"
						            Name = "menuHelpLogSwitch"
						            Text = "Enable Log(&amp;L)"
						            />

						        <UiToolStripMenuItem id="menuHelpLogOpen"
						            Name = "menuHelpLogOpen"
						            Text = "Open(&amp;O)"
						            />

						        <UiToolStripMenuItem id="menuHelpDebug"
						            Name = "menuHelpDebug"
						            Text = "Debug"
						            Visible = "false"
						            />
				            </_DropDownItems>
				        </UiToolStripMenuItem>
		            </_DropDownItems>
		        </UiToolStripMenuItem>

		        <UiToolStripMenuItem id="menuHidden"
		            Name = "menuHidden"
		            Text = "MenuHidden"
		            Visible = "false"
		            >
		            <_DropDownItems>

				        <UiToolStripMenuItem id="menuHiddenEditLyric"
				            Name = "menuHiddenEditLyric"
				            ShortcutKeys = "F2"
				            Text = "Start Lyric Input"
				            Visible = "false"
				            />

				        <UiToolStripMenuItem id="menuHiddenEditFlipToolPointerPencil"
				            Name = "menuHiddenEditFlipToolPointerPencil"
				            ShortcutKeys = "Control,W"
				            Text = "Change Tool Pointer / Pencil"
				            Visible = "false"
				            />

				        <UiToolStripMenuItem id="menuHiddenEditFlipToolPointerEraser"
				            Name = "menuHiddenEditFlipToolPointerEraser"
				            ShortcutKeys = "Control,E"
				            Text = "Change Tool Pointer/ Eraser"
				            Visible = "false"
				            />

				        <UiToolStripMenuItem id="menuHiddenVisualForwardParameter"
				            Name = "menuHiddenVisualForwardParameter"
				            ShortcutKeys = "Control,Alt,Next"
				            Text = "Next Control Curve"
				            Visible = "false"
				            />

				        <UiToolStripMenuItem id="menuHiddenVisualBackwardParameter"
				            Name = "menuHiddenVisualBackwardParameter"
				            ShortcutKeys = "Control,Alt,PageUp"
				            Text = "Previous Control Curve"
				            Visible = "false"
				            />

				        <UiToolStripMenuItem id="menuHiddenTrackNext"
				            Name = "menuHiddenTrackNext"
				            ShortcutKeys = "Control,Next"
				            Text = "Next Track"
				            Visible = "false"
				            />

				        <UiToolStripMenuItem id="menuHiddenTrackBack"
				            Name = "menuHiddenTrackBack"
				            ShortcutKeys = "Control,PageUp"
				            Text = "Previous Track"
				            Visible = "false"
				            />

				        <UiToolStripMenuItem id="menuHiddenCopy"
				            Name = "menuHiddenCopy"
				            Text = "Copy"
				            />

				        <UiToolStripMenuItem id="menuHiddenPaste"
				            Name = "menuHiddenPaste"
				            Text = "Paste"
				            />

				        <UiToolStripMenuItem id="menuHiddenCut"
				            Name = "menuHiddenCut"
				            Text = "Cut"
				            />

				        <UiToolStripMenuItem id="menuHiddenSelectForward"
				            Name = "menuHiddenSelectForward"
				            ShortcutKeys = "Alt,Right"
				            Text = "Select Forward"
				            />

				        <UiToolStripMenuItem id="menuHiddenSelectBackward"
				            Name = "menuHiddenSelectBackward"
				            ShortcutKeys = "Alt,Left"
				            Text = "Select Backward"
				            />

				        <UiToolStripMenuItem id="menuHiddenMoveUp"
				            Name = "menuHiddenMoveUp"
				            Text = "Move Up"
				            />

				        <UiToolStripMenuItem id="menuHiddenMoveDown"
				            Name = "menuHiddenMoveDown"
				            Text = "Move Down"
				            />

				        <UiToolStripMenuItem id="menuHiddenMoveLeft"
				            Name = "menuHiddenMoveLeft"
				            Text = "Move Left"
				            />

				        <UiToolStripMenuItem id="menuHiddenMoveRight"
				            Name = "menuHiddenMoveRight"
				            Text = "Move Right"
				            />

				        <UiToolStripMenuItem id="menuHiddenLengthen"
				            Name = "menuHiddenLengthen"
				            Text = "Lengthen"
				            />

				        <UiToolStripMenuItem id="menuHiddenShorten"
				            Name = "menuHiddenShorten"
				            Text = "Shorten"
				            />

				        <UiToolStripMenuItem id="menuHiddenGoToStartMarker"
				            Name = "menuHiddenGoToStartMarker"
				            Text = "GoTo Start Marker"
				            />

				        <UiToolStripMenuItem id="menuHiddenGoToEndMarker"
				            Name = "menuHiddenGoToEndMarker"
				            Text = "GoTo End Marker"
				            />

				        <UiToolStripMenuItem id="menuHiddenPlayFromStartMarker"
				            Name = "menuHiddenPlayFromStartMarker"
				            Text = "Play From Start Marker"
				            />

				        <UiToolStripMenuItem id="menuHiddenFlipCurveOnPianorollMode"
				            Name = "menuHiddenFlipCurveOnPianorollMode"
				            Text = "Change pitch drawing mode"
				            />

				        <UiToolStripMenuItem id="menuHiddenPrintPoToCSV"
				            Name = "menuHiddenPrintPoToCSV"
				            Text = "Print language configs to CSV"
				            />
		            </_DropDownItems>
		        </UiToolStripMenuItem>
            </_Items>
          </UiMenuStrip>
      </_MainMenuStrip>
	</Form>

	<!-- programmatically initialized -->
    <UiContextMenuStrip id="stripDDBtnQuantize"
            >
        <_Items>
	        <UiToolStripMenuItem id="stripDDBtnQuantize04"
	            Text = "1/4"
	            />

	        <UiToolStripMenuItem id="stripDDBtnQuantize08"
	            Text = "1/8"
	            />

	        <UiToolStripMenuItem id="stripDDBtnQuantize16"
	            Text = "1/16"
	            />

	        <UiToolStripMenuItem id="stripDDBtnQuantize32"
	            Text = "1/32"
	            />

	        <UiToolStripMenuItem id="stripDDBtnQuantize64"
	            Text = "1/64"
	            />

	        <UiToolStripMenuItem id="stripDDBtnQuantize128"
	            Text = "1/128"
	            />

	        <UiToolStripMenuItem id="stripDDBtnQuantizeOff"
	            Text = "Off"
	            />

	        <UiToolStripMenuItem id="menuItem2"
	            Text = "-"
	            />

	        <UiToolStripMenuItem id="stripDDBtnQuantizeTriplet"
	            Text = "Triplet"
	            />
        </_Items>
    </UiContextMenuStrip>

    <!-- programmatically instantiated and shown -->
    <UiContextMenuStrip id="cMenuPiano"
            Name = "cMenuPiano"
            RenderMode = "System"
            ShowCheckMargin = "true"
            ShowImageMargin = "false"
            Size = "(242, 458)"
            >
        <_Items>

	        <UiToolStripMenuItem id="cMenuPianoPointer"

	            Name = "cMenuPianoPointer"
	            Size = "(241, 22)"
	            Text = "Arrow(&amp;A)"
	            />

	        <UiToolStripMenuItem id="cMenuPianoPencil"

	            Name = "cMenuPianoPencil"
	            Size = "(241, 22)"
	            Text = "Pencil(&amp;W)"
	            />

	        <UiToolStripMenuItem id="cMenuPianoEraser"

	            Name = "cMenuPianoEraser"
	            Size = "(241, 22)"
	            Text = "Eraser(&amp;E)"
	            />

	        <UiToolStripMenuItem id="cMenuPianoPaletteTool"

	            Name = "cMenuPianoPaletteTool"
	            Size = "(241, 22)"
	            Text = "Palette Tool"
	            />

	        <UiToolStripSeparator id="toolStripSeparator15"

	            Name = "toolStripSeparator15"
	            Size = "(238, 6)"
	            />

	        <UiToolStripMenuItem id="cMenuPianoCurve"

	            Name = "cMenuPianoCurve"
	            Size = "(241, 22)"
	            Text = "Curve(&amp;V)"
	            />

	        <UiToolStripSeparator id="toolStripMenuItem13"

	            Name = "toolStripMenuItem13"
	            Size = "(238, 6)"
	            />

	        <UiToolStripMenuItem id="cMenuPianoFixed"
	            Name = "cMenuPianoFixed"
	            Size = "(241, 22)"
	            Text = "Note Fixed Length(&amp;N)"
	            >
	            <_DropDownItems>
			        <UiToolStripMenuItem id="cMenuPianoFixed01"

			            Name = "cMenuPianoFixed01"
			            Size = "(141, 22)"
			            Text = "1/ 1 [1920]"
			            />

			        <UiToolStripMenuItem id="cMenuPianoFixed02"

			            Name = "cMenuPianoFixed02"
			            Size = "(141, 22)"
			            Text = "1/ 2 [960]"
			            />

			        <UiToolStripMenuItem id="cMenuPianoFixed04"

			            Name = "cMenuPianoFixed04"
			            Size = "(141, 22)"
			            Text = "1/ 4 [480]"
			            />

			        <UiToolStripMenuItem id="cMenuPianoFixed08"

			            Name = "cMenuPianoFixed08"
			            Size = "(141, 22)"
			            Text = "1/ 8 [240]"
			            />

			        <UiToolStripMenuItem id="cMenuPianoFixed16"

			            Name = "cMenuPianoFixed16"
			            Size = "(141, 22)"
			            Text = "1/16 [120]"
			            />

			        <UiToolStripMenuItem id="cMenuPianoFixed32"

			            Name = "cMenuPianoFixed32"
			            Size = "(141, 22)"
			            Text = "1/32 [60]"
			            />

			        <UiToolStripMenuItem id="cMenuPianoFixed64"

			            Name = "cMenuPianoFixed64"
			            Size = "(141, 22)"
			            Text = "1/64 [30]"
			            />

			        <UiToolStripMenuItem id="cMenuPianoFixed128"

			            Name = "cMenuPianoFixed128"
			            Size = "(141, 22)"
			            Text = "1/128[15]"
			            />

			        <UiToolStripMenuItem id="cMenuPianoFixedOff"

			            Name = "cMenuPianoFixedOff"
			            Size = "(141, 22)"
			            Text = "オフ"
			            />

			        <UiToolStripSeparator id="toolStripMenuItem18"

			            Name = "toolStripMenuItem18"
			            Size = "(138, 6)"
			            />

			        <UiToolStripMenuItem id="cMenuPianoFixedTriplet"

			            Name = "cMenuPianoFixedTriplet"
			            Size = "(141, 22)"
			            Text = "3連符"
			            />

			        <UiToolStripMenuItem id="cMenuPianoFixedDotted"

			            Name = "cMenuPianoFixedDotted"
			            Size = "(141, 22)"
			            Text = "付点"
			            />
	            </_DropDownItems>
            </UiToolStripMenuItem>

	        <UiToolStripMenuItem id="cMenuPianoQuantize"
	            Name = "cMenuPianoQuantize"
	            Size = "(241, 22)"
	            Text = "Quantize(&amp;Q)"
	            >
	            <_DropDownItems>

			        <UiToolStripMenuItem id="cMenuPianoQuantize04"

			            Name = "cMenuPianoQuantize04"
			            Size = "(109, 22)"
			            Text = "1/4"
			            />

			        <UiToolStripMenuItem id="cMenuPianoQuantize08"

			            Name = "cMenuPianoQuantize08"
			            Size = "(109, 22)"
			            Text = "1/8"
			            />

			        <UiToolStripMenuItem id="cMenuPianoQuantize16"

			            Name = "cMenuPianoQuantize16"
			            Size = "(109, 22)"
			            Text = "1/16"
			            />

			        <UiToolStripMenuItem id="cMenuPianoQuantize32"

			            Name = "cMenuPianoQuantize32"
			            Size = "(109, 22)"
			            Text = "1/32"
			            />

			        <UiToolStripMenuItem id="cMenuPianoQuantize64"

			            Name = "cMenuPianoQuantize64"
			            Size = "(109, 22)"
			            Text = "1/64"
			            />

			        <UiToolStripMenuItem id="cMenuPianoQuantize128"

			            Name = "cMenuPianoQuantize128"
			            Size = "(109, 22)"
			            Text = "1/128"
			            />

			        <UiToolStripMenuItem id="cMenuPianoQuantizeOff"

			            Name = "cMenuPianoQuantizeOff"
			            Size = "(109, 22)"
			            Text = "オフ"
			            />

			        <UiToolStripSeparator id="toolStripMenuItem26"

			            Name = "toolStripMenuItem26"
			            Size = "(106, 6)"
			            />

			        <UiToolStripMenuItem id="cMenuPianoQuantizeTriplet"

			            Name = "cMenuPianoQuantizeTriplet"
			            Size = "(109, 22)"
			            Text = "3連符"
			            />
	            </_DropDownItems>
            </UiToolStripMenuItem>

	        <UiToolStripMenuItem id="cMenuPianoGrid"

	            Name = "cMenuPianoGrid"
	            Size = "(241, 22)"
	            Text = "Show/Hide Grid Line(&amp;S)"
	            />

	        <UiToolStripSeparator id="toolStripMenuItem14"

	            Name = "toolStripMenuItem14"
	            Size = "(238, 6)"
	            />

	        <UiToolStripMenuItem id="cMenuPianoUndo"

	            Name = "cMenuPianoUndo"
	            Size = "(241, 22)"
	            Text = "Undo(&amp;U)"
	            />

	        <UiToolStripMenuItem id="cMenuPianoRedo"

	            Name = "cMenuPianoRedo"
	            Size = "(241, 22)"
	            Text = "Redo(&amp;R)"
	            />

	        <UiToolStripSeparator id="toolStripMenuItem15"

	            Name = "toolStripMenuItem15"
	            Size = "(238, 6)"
	            />

	        <UiToolStripMenuItem id="cMenuPianoCut"

	            Name = "cMenuPianoCut"
	            Size = "(241, 22)"
	            Text = "Cut(&amp;T)"
	            />

	        <UiToolStripMenuItem id="cMenuPianoCopy"

	            Name = "cMenuPianoCopy"
	            Size = "(241, 22)"
	            Text = "Copy(&amp;C)"
	            />

	        <UiToolStripMenuItem id="cMenuPianoPaste"

	            Name = "cMenuPianoPaste"
	            Size = "(241, 22)"
	            Text = "Paste(&amp;P)"
	            />

	        <UiToolStripMenuItem id="cMenuPianoDelete"

	            Name = "cMenuPianoDelete"
	            Size = "(241, 22)"
	            Text = "Delete(&amp;D)"
	            />

	        <UiToolStripSeparator id="toolStripMenuItem16"

	            Name = "toolStripMenuItem16"
	            Size = "(238, 6)"
	            />

	        <UiToolStripMenuItem id="cMenuPianoSelectAll"

	            Name = "cMenuPianoSelectAll"
	            Size = "(241, 22)"
	            Text = "Select All(&amp;A)"
	            />

	        <UiToolStripMenuItem id="cMenuPianoSelectAllEvents"

	            Name = "cMenuPianoSelectAllEvents"
	            Size = "(241, 22)"
	            Text = "Select All Events(&amp;E)"
	            />

	        <UiToolStripSeparator id="toolStripMenuItem17"

	            Name = "toolStripMenuItem17"
	            Size = "(238, 6)"
	            />

	        <UiToolStripMenuItem id="cMenuPianoImportLyric"

	            Name = "cMenuPianoImportLyric"
	            Size = "(241, 22)"
	            Text = "Insert Lyrics(&amp;L)"
	            />

	        <UiToolStripMenuItem id="cMenuPianoExpressionProperty"

	            Name = "cMenuPianoExpressionProperty"
	            Size = "(241, 22)"
	            Text = "Note Expression Property(&amp;P)"
	            />

	        <UiToolStripMenuItem id="cMenuPianoVibratoProperty"

	            Name = "cMenuPianoVibratoProperty"
	            Size = "(241, 22)"
	            Text = "Note Vibrato Property"
	            />
        </_Items>
    </UiContextMenuStrip>

    <UiContextMenuStrip id="cMenuTrackTab"
            Name = "cMenuTrackTab"
            RenderMode = "System"
            ShowCheckMargin = "true"
            ShowImageMargin = "false"
            Size = "(220, 220)"
        >
        <_Items>

	        <UiToolStripMenuItem id="cMenuTrackTabTrackOn"

	            Name = "cMenuTrackTabTrackOn"
	            Size = "(219, 22)"
	            Text = "Track On(&amp;K)"
	            />

	        <UiToolStripSeparator id="toolStripMenuItem24"

	            Name = "toolStripMenuItem24"
	            Size = "(216, 6)"
	            />

	        <UiToolStripMenuItem id="cMenuTrackTabAdd"

	            Name = "cMenuTrackTabAdd"
	            Size = "(219, 22)"
	            Text = "Add Track(&amp;A)"
	            />

	        <UiToolStripMenuItem id="cMenuTrackTabCopy"

	            Name = "cMenuTrackTabCopy"
	            Size = "(219, 22)"
	            Text = "Copy Track(&amp;C)"
	            />

	        <UiToolStripMenuItem id="cMenuTrackTabChangeName"

	            Name = "cMenuTrackTabChangeName"
	            Size = "(219, 22)"
	            Text = "Rename Track"
	            />

	        <UiToolStripMenuItem id="cMenuTrackTabDelete"

	            Name = "cMenuTrackTabDelete"
	            Size = "(219, 22)"
	            Text = "Delete Track(&amp;D)"
	            />

	        <UiToolStripSeparator id="toolStripMenuItem25"

	            Name = "toolStripMenuItem25"
	            Size = "(216, 6)"
	            />

	        <UiToolStripMenuItem id="cMenuTrackTabRenderCurrent"

	            Name = "cMenuTrackTabRenderCurrent"
	            Size = "(219, 22)"
	            Text = "Render Current Track(&amp;T)"
	            />

	        <UiToolStripMenuItem id="cMenuTrackTabRenderAll"

	            Name = "cMenuTrackTabRenderAll"
	            Size = "(219, 22)"
	            Text = "Render All Tracks(&amp;S)"
	            />

	        <UiToolStripSeparator id="toolStripMenuItem27"

	            Name = "toolStripMenuItem27"
	            Size = "(216, 6)"
	            />

	        <UiToolStripMenuItem id="cMenuTrackTabOverlay"

	            Name = "cMenuTrackTabOverlay"
	            Size = "(219, 22)"
	            Text = "Overlay(&amp;O)"
	            />

	        <UiToolStripMenuItem id="cMenuTrackTabRenderer"
	            Name = "cMenuTrackTabRenderer"
	            Size = "(219, 22)"
	            Text = "Renderer(&amp;R)"
	            >
	            <_DropDownItems>
			        <UiToolStripMenuItem id="cMenuTrackTabRendererVOCALOID1"

			            Name = "cMenuTrackTabRendererVOCALOID1"
			            Size = "(197, 22)"
			            Text = "VOCALOID1(&amp;1)"
			            />

			        <UiToolStripMenuItem id="cMenuTrackTabRendererVOCALOID2"

			            Name = "cMenuTrackTabRendererVOCALOID2"
			            Size = "(197, 22)"
			            Text = "VOCALOID2(&amp;2)"
			            />

			        <UiToolStripMenuItem id="cMenuTrackTabRendererUtau"

			            Name = "cMenuTrackTabRendererUtau"
			            Size = "(197, 22)"
			            Text = "UTAU(&amp;3)"
			            />

			        <UiToolStripMenuItem id="cMenuTrackTabRendererStraight"

			            Name = "cMenuTrackTabRendererStraight"
			            Size = "(197, 22)"
			            Text = "vConnect-STAND(&amp;4) "
			            />

			        <UiToolStripMenuItem id="cMenuTrackTabRendererAquesTone"

			            Name = "cMenuTrackTabRendererAquesTone"
			            Size = "(197, 22)"
			            Text = "AquesTone(&amp;5)"
			            />

			        <UiToolStripMenuItem id="cMenuTrackTabRendererAquesTone2"

			            Name = "cMenuTrackTabRendererAquesTone2"
			            Size = "(197, 22)"
			            Text = "AquesTone2(&amp;6)"
			            />
	            </_DropDownItems>
            </UiToolStripMenuItem>
        </_Items>
    </UiContextMenuStrip>

    <UiContextMenuStrip id="cMenuTrackSelector"
            Name = "cMenuTrackSelector"
            RenderMode = "System"
            ShowCheckMargin = "true"
            ShowImageMargin = "false"
            Size = "(206, 336)"
        >
        <_Items>
	        <UiToolStripMenuItem id="cMenuTrackSelectorPointer"

	            Name = "cMenuTrackSelectorPointer"
	            Size = "(205, 22)"
	            Text = "Arrow(&amp;A)"
	            />

	        <UiToolStripMenuItem id="cMenuTrackSelectorPencil"

	            Name = "cMenuTrackSelectorPencil"
	            Size = "(205, 22)"
	            Text = "Pencil(&amp;W)"
	            />

	        <UiToolStripMenuItem id="cMenuTrackSelectorLine"

	            Name = "cMenuTrackSelectorLine"
	            Size = "(205, 22)"
	            Text = "Line(&amp;L)"
	            />

	        <UiToolStripMenuItem id="cMenuTrackSelectorEraser"

	            Name = "cMenuTrackSelectorEraser"
	            Size = "(205, 22)"
	            Text = "Eraser(&amp;E)"
	            />

	        <UiToolStripMenuItem id="cMenuTrackSelectorPaletteTool"

	            Name = "cMenuTrackSelectorPaletteTool"
	            Size = "(205, 22)"
	            Text = "Palette Tool"
	            />

	        <UiToolStripSeparator id="toolStripSeparator14"

	            Name = "toolStripSeparator14"
	            Size = "(202, 6)"
	            />

	        <UiToolStripMenuItem id="cMenuTrackSelectorCurve"

	            Name = "cMenuTrackSelectorCurve"
	            Size = "(205, 22)"
	            Text = "Curve(&amp;V)"
	            />

	        <UiToolStripSeparator id="toolStripMenuItem28"

	            Name = "toolStripMenuItem28"
	            Size = "(202, 6)"
	            />

	        <UiToolStripMenuItem id="cMenuTrackSelectorUndo"

	            Name = "cMenuTrackSelectorUndo"
	            Size = "(205, 22)"
	            Text = "Undo(&amp;U)"
	            />

	        <UiToolStripMenuItem id="cMenuTrackSelectorRedo"

	            Name = "cMenuTrackSelectorRedo"
	            Size = "(205, 22)"
	            Text = "Redo(&amp;R)"
	            />

	        <UiToolStripSeparator id="toolStripMenuItem29"

	            Name = "toolStripMenuItem29"
	            Size = "(202, 6)"
	            />

	        <UiToolStripMenuItem id="cMenuTrackSelectorCut"

	            Name = "cMenuTrackSelectorCut"
	            Size = "(205, 22)"
	            Text = "Cut(&amp;T)"
	            />

	        <UiToolStripMenuItem id="cMenuTrackSelectorCopy"

	            Name = "cMenuTrackSelectorCopy"
	            Size = "(205, 22)"
	            Text = "Copy(&amp;C)"
	            />

	        <UiToolStripMenuItem id="cMenuTrackSelectorPaste"

	            Name = "cMenuTrackSelectorPaste"
	            Size = "(205, 22)"
	            Text = "Paste(&amp;P)"
	            />

	        <UiToolStripMenuItem id="cMenuTrackSelectorDelete"

	            Name = "cMenuTrackSelectorDelete"
	            Size = "(205, 22)"
	            Text = "Delete(&amp;D)"
	            />

	        <UiToolStripMenuItem id="cMenuTrackSelectorDeleteBezier"

	            Name = "cMenuTrackSelectorDeleteBezier"
	            Size = "(205, 22)"
	            Text = "Delete Bezier Point(&amp;B)"
	            />

	        <UiToolStripSeparator id="toolStripMenuItem31"

	            Name = "toolStripMenuItem31"
	            Size = "(202, 6)"
	            />

	        <UiToolStripMenuItem id="cMenuTrackSelectorSelectAll"

	            Name = "cMenuTrackSelectorSelectAll"
	            Size = "(205, 22)"
	            Text = "Select All Events(&amp;E)"
	            />
        </_Items>
    </UiContextMenuStrip>

    <UiContextMenuStrip id="cMenuPositionIndicator"
            Name = "cMenuTrackTab"
            RenderMode = "System"
            ShowImageMargin = "false"
            Size = "(151, 48)"
        >
        <_Items>
	        <UiToolStripMenuItem id="cMenuPositionIndicatorStartMarker"

	            Name = "cMenuPositionIndicatorStartMarker"
	            Size = "(150, 22)"
	            Text = "Set start marker"
	            />

	        <UiToolStripMenuItem id="cMenuPositionIndicatorEndMarker"

	            Name = "cMenuPositionIndicatorEndMarker"
	            Size = "(150, 22)"
	            Text = "Set end marker"
	            />
        </_Items>
    </UiContextMenuStrip>

<____UNKNOWN____>

		<!-- No known place to be used -->
        <UiToolStripSeparator id="toolStripSeparator2"

            Name = "toolStripSeparator2"
            Size = "(57, 6)"
            />

		<!-- No known place to be used -->
        <UiToolStripSeparator id="toolStripSeparator3"

            Name = "toolStripSeparator3"
            Size = "(57, 6)"
            />

		<!-- No known place to be used -->
	    <UiImageList id="imageListMenu"

            ColorDepth = "Depth8Bit"
            ImageSize = "(1, 16)"
	            TransparentColor = "$Transparent"
	            />

	    

    </____UNKNOWN____>

</Widgets>
